pastepwn/__init__.py
pastepwn/version.py
pastepwn/actions/__init__.py
pastepwn/actions/basicaction.py
pastepwn/actions/databaseaction.py
pastepwn/actions/discordaction.py
pastepwn/actions/emailaction.py
pastepwn/actions/genericaction.py
pastepwn/actions/ircaction.py
pastepwn/actions/logaction.py
pastepwn/actions/mispaction.py
pastepwn/actions/savefileaction.py
pastepwn/actions/savejsonaction.py
pastepwn/actions/syslogaction.py
pastepwn/actions/telegramaction.py
pastepwn/actions/twitteraction.py
pastepwn/actions/webhookaction.py
pastepwn/actions/tests/__init__.py
pastepwn/actions/tests/discordaction_test.py
pastepwn/actions/tests/savefileaction_test.py
pastepwn/actions/tests/savejsonaction_test.py
pastepwn/analyzers/__init__.py
pastepwn/analyzers/adobekeyanalyzer.py
pastepwn/analyzers/alwaystrueanalyzer.py
pastepwn/analyzers/awsaccesskeyanalyzer.py
pastepwn/analyzers/awssecretkeyanalyzer.py
pastepwn/analyzers/awssessiontokenanalyzer.py
pastepwn/analyzers/azuresubscriptionkeyanalyzer.py
pastepwn/analyzers/base64analyzer.py
pastepwn/analyzers/base64asciianalyzer.py
pastepwn/analyzers/basicanalyzer.py
pastepwn/analyzers/battlenetkeyanalyzer.py
pastepwn/analyzers/bcrypthashanalyzer.py
pastepwn/analyzers/creditcardanalyzer.py
pastepwn/analyzers/databasedumpanalyzer.py
pastepwn/analyzers/dbconnstringanalyzer.py
pastepwn/analyzers/emailpasswordpairanalyzer.py
pastepwn/analyzers/epickeyanalyzer.py
pastepwn/analyzers/exactwordanalyzer.py
pastepwn/analyzers/facebookaccesstokenanalyzer.py
pastepwn/analyzers/genericanalyzer.py
pastepwn/analyzers/googleapikeyanalyzer.py
pastepwn/analyzers/googleoauthkeyanalyzer.py
pastepwn/analyzers/hashanalyzer.py
pastepwn/analyzers/ibananalyzer.py
pastepwn/analyzers/ipv4addressanalyzer.py
pastepwn/analyzers/mailanalyzer.py
pastepwn/analyzers/mailchimpapikeyanalyzer.py
pastepwn/analyzers/md5hashanalyzer.py
pastepwn/analyzers/megalinkanalyzer.py
pastepwn/analyzers/microsoftkeyanalyzer.py
pastepwn/analyzers/originkeyanalyzer.py
pastepwn-2.1.0.dist-info/LICENSE
pastepwn-2.1.0.dist-info/METADATA
pastepwn-2.1.0.dist-info/WHEEL
pastepwn-2.1.0.dist-info/top_level.txt
pastepwn-2.1.0.dist-info/RECORD
