Metadata-Version: 2.1
Name: pastepwn
Version: 2.1.0
Summary: Python framework to scrape PasteBin pastes and analyze them
Home-page: https://github.com/d-Rickyy-b/pastepwn
Author: d-Rickyy-b
Author-email: pastepwn@rico-j.de
License: MIT
Keywords: python pastebin scraping osint framework
Classifier: Development Status :: 5 - Production/Stable
Classifier: Environment :: Console
Classifier: Intended Audience :: Developers
Classifier: Intended Audience :: Science/Research
Classifier: License :: OSI Approved :: MIT License
Classifier: Operating System :: OS Independent
Classifier: Topic :: Software Development :: Libraries :: Python Modules
Classifier: Topic :: Security
Classifier: Topic :: Internet
Classifier: Programming Language :: Python
Classifier: Programming Language :: Python :: 3.9
Classifier: Programming Language :: Python :: 3.10
Classifier: Programming Language :: Python :: 3.11
License-File: LICENSE
Requires-Dist: requests (==2.28.1)
